cloudscale/__init__.py
cloudscale/cli.py
cloudscale/client.py
cloudscale/error.py
cloudscale/log.py
cloudscale/util.py
cloudscale/version.py
cloudscale/commands/__init__.py
cloudscale/commands/flavor.py
cloudscale/commands/floating_ip.py
cloudscale/commands/image.py
cloudscale/commands/network.py
cloudscale/commands/objects_user.py
cloudscale/commands/region.py
cloudscale/commands/server.py
cloudscale/commands/server_group.py
cloudscale/commands/subnet.py
cloudscale/commands/volume.py
cloudscale/lib/__init__.py
cloudscale/lib/flavor.py
cloudscale/lib/floating_ip.py
cloudscale/lib/image.py
cloudscale/lib/network.py
cloudscale/lib/objects_user.py
cloudscale/lib/region.py
cloudscale/lib/server.py
cloudscale/lib/server_group.py
cloudscale/lib/subnet.py
cloudscale/lib/volume.py
cloudscale/tests/__init__.py
cloudscale/tests/test_common.py
cloudscale/tests/test_flavor.py
cloudscale/tests/test_floating_ip.py
cloudscale/tests/test_image.py
cloudscale/tests/test_network.py
cloudscale/tests/test_objects_user.py
cloudscale/tests/test_region.py
cloudscale/tests/test_server.py
cloudscale/tests/test_server_group.py
cloudscale/tests/test_subnet.py
cloudscale/tests/test_version.py
cloudscale/tests/test_volume.py
cloudscale-0.15.0.dist-info/DESCRIPTION.rst
cloudscale-0.15.0.dist-info/LICENSE.txt
cloudscale-0.15.0.dist-info/METADATA
cloudscale-0.15.0.dist-info/RECORD
cloudscale-0.15.0.dist-info/WHEEL
cloudscale-0.15.0.dist-info/entry_points.txt
cloudscale-0.15.0.dist-info/metadata.json
cloudscale-0.15.0.dist-info/top_level.txt
