Metadata-Version: 2.0
Name: cloudscale
Version: 0.15.0
Summary: A library and command line interface for cloudscale.ch
Home-page: https://github.com/cloudscale-ch/python-cloudscale
Author: René Moser
Author-email: mail@renemoser.net
License: MIT
Platform: UNKNOWN
Classifier: Intended Audience :: Developers
Classifier: Intended Audience :: System Administrators
Classifier: Development Status :: 4 - Beta
Classifier: Programming Language :: Python :: 3
Classifier: License :: OSI Approved :: MIT License
Classifier: Operating System :: OS Independent
Classifier: Environment :: Console
Requires-Python: >=3.6
Provides-Extra: highlight
Requires-Dist: click (>=7.0.0)
Requires-Dist: jmespath
Requires-Dist: pygments
Requires-Dist: requests
Requires-Dist: tabulate
Requires-Dist: yaspin
Provides-Extra: highlight
Requires-Dist: pygments; extra == 'highlight'
